rich_argparse_plus/__init__.py
rich_argparse_plus/example_parser.py
rich_argparse_plus/help_renderer.py
rich_argparse_plus/rich_help_formatter_plus.py
rich_argparse_plus/theme_scripts.py
rich_argparse_plus/themes.py
rich_argparse_plus-0.3.1.4.dist-info/entry_points.txt
rich_argparse_plus-0.3.1.4.dist-info/LICENSE
rich_argparse_plus-0.3.1.4.dist-info/WHEEL
rich_argparse_plus-0.3.1.4.dist-info/METADATA
rich_argparse_plus-0.3.1.4.dist-info/RECORD
