Metadata-Version: 2.1
Name: rich_argparse_plus
Version: 0.3.1.4
Summary: A rich text formatter for argparse help with export and default features
Keywords: argparse,colors,help-formatter,help,rich
Author-email: Ali Hamdan <ali.hamdan.dev@gmail.com>, Michel de Cryptadamus <michel@cryptadamus.com>
Requires-Python: >=3.7
Classifier: Development Status :: 4 - Beta
Classifier: Environment :: Console
Classifier: Intended Audience :: Developers
Classifier: License :: OSI Approved :: MIT License
Classifier: Operating System :: OS Independent
Classifier: Programming Language :: Python :: 3.7
Classifier: Programming Language :: Python :: 3.8
Classifier: Programming Language :: Python :: 3.9
Classifier: Programming Language :: Python :: 3.10
Classifier: Programming Language :: Python :: 3.11
Requires-Dist: rich >= 11.0.0
Requires-Dist: flit ~= 3.7 ; extra == "dev"
Requires-Dist: keyring ~= 23.9 ; extra == "dev"
Requires-Dist: pytest-cov ; extra == "dev"
Requires-Dist: pytest ; extra == "dev"
Requires-Dist: cairosvg ~= 2.5 ; extra == "optional"
Project-URL: Home, https://github.com/michelcrypt4d4mus/rich-argparse-plus
Provides-Extra: dev
Provides-Extra: optional
